thumbny/__init__.py
thumbny/__main__.py
thumbny/arguments_parser/__init__.py
thumbny/arguments_parser/create.py
thumbny/arguments_parser/delete.py
thumbny/arguments_parser/generate.py
thumbny/arguments_parser/info.py
thumbny/arguments_parser/templates.py
thumbny/base/__init__.py
thumbny/base/command.py
thumbny/base/runner.py
thumbny/commands/__init__.py
thumbny/commands/create.py
thumbny/commands/delete.py
thumbny/commands/generate.py
thumbny/commands/info.py
thumbny/commands/templates.py
thumbny/enums/__init__.py
thumbny/enums/position.py
thumbny/exceptions/__init__.py
thumbny/models/__init__.py
thumbny/models/filler.py
thumbny/models/shared.py
thumbny/models/template.py
thumbny/models/template_name.py
thumbny/models/validation/__init__.py
thumbny/templates_manager/__init__.py
thumbny/templates_manager/file_handler.py
thumbny/templates_manager/validator.py
thumbny-1.3.2.dist-info/LICENSE
thumbny-1.3.2.dist-info/METADATA
thumbny-1.3.2.dist-info/WHEEL
thumbny-1.3.2.dist-info/entry_points.txt
thumbny-1.3.2.dist-info/top_level.txt
thumbny-1.3.2.dist-info/RECORD
