Metadata-Version: 2.1
Name: thumbny
Version: 1.3.2
Summary: Social Thumbnails Generator
Home-page: https://github.com/maltarouti/thumbny
Author: Murtada Altarouti
Author-email: murtada.altarouti@gmail.com
License: MIT
Requires-Python: >=3.9
License-File: LICENSE
Requires-Dist: Pillow>=11.0.0
